pip_services4_gcp/__init__.py
pip_services4_gcp/clients/CloudFunctionClient.py
pip_services4_gcp/clients/CommandableCloudFunctionClient.py
pip_services4_gcp/clients/__init__.py
pip_services4_gcp/connect/GcpConnectionParams.py
pip_services4_gcp/connect/GcpConnectionResolver.py
pip_services4_gcp/connect/__init__.py
pip_services4_gcp/containers/CloudFunction.py
pip_services4_gcp/containers/CloudFunctionRequestHelper.py
pip_services4_gcp/containers/CommandableCloudFunction.py
pip_services4_gcp/containers/__init__.py
pip_services4_gcp/controller/CloudFunctionAction.py
pip_services4_gcp/controller/CloudFunctionController.py
pip_services4_gcp/controller/CommandableCloudFunctionController.py
pip_services4_gcp/controller/ICloudFunctionController.py
pip_services4_gcp/controller/__init__.py
pip_services4_gcp-0.0.1.dist-info/LICENSE
pip_services4_gcp-0.0.1.dist-info/METADATA
pip_services4_gcp-0.0.1.dist-info/WHEEL
pip_services4_gcp-0.0.1.dist-info/top_level.txt
pip_services4_gcp-0.0.1.dist-info/zip-safe
pip_services4_gcp-0.0.1.dist-info/RECORD
