Metadata-Version: 2.1
Name: pip-services4-gcp
Version: 0.0.1
Summary: Google Cloud components for Pip.Services in Python
Home-page: http://github.com/pip-services4/pip-services4-python/tree/main/pip-services4-gcp-python
Author: Conceptual Vision Consulting LLC
Author-email: seroukhov@gmail.com
License: MIT
Platform: any
Classifier: Development Status :: 4 - Beta
Classifier: Intended Audience :: Developers
Classifier: License :: OSI Approved :: MIT License
Classifier: Operating System :: OS Independent
Classifier: Programming Language :: Python
Classifier: Programming Language :: Python :: 3.6
Classifier: Programming Language :: Python :: 3.7
Classifier: Programming Language :: Python :: 3.8
Classifier: Programming Language :: Python :: 3.9
Classifier: Topic :: Software Development :: Libraries :: Python Modules
License-File: LICENSE
Requires-Dist: Flask <3.0,>=2.0.3
Requires-Dist: pip-services4-commons <1.0,>=0.0.1
Requires-Dist: pip-services4-components <1.0,>=0.0.1
Requires-Dist: pip-services4-config <1.0,>=0.0.1
Requires-Dist: pip-services4-data <1.0,>=0.0.1
Requires-Dist: pip-services4-http <1.0,>=0.0.1
Requires-Dist: pip-services4-observability <1.0,>=0.0.1
Requires-Dist: pip-services4-container <1.0,>=0.0.1
Requires-Dist: pip-services4-rpc <1.0,>=0.0.1
